README.md
setup.py
deployz/__init__.py
deployz/deployer.py
deployz/fast_api.py
deployz/flask_api.py
deployz/utils.py
deployz.egg-info/PKG-INFO
deployz.egg-info/SOURCES.txt
deployz.egg-info/dependency_links.txt
deployz.egg-info/entry_points.txt
deployz.egg-info/requires.txt
deployz.egg-info/top_level.txt
deployz/executors/__init__.py
deployz/executors/argo_training_executor.py
deployz/executors/executor.py
deployz/executors/training_executor.py